podme_api/__init__.py
podme_api/__version__.py
podme_api/auth/__init__.py
podme_api/auth/client.py
podme_api/auth/common.py
podme_api/auth/models.py
podme_api/auth/utils.py
podme_api/cli/__init__.py
podme_api/cli/cli.py
podme_api/cli/utils.py
podme_api/client.py
podme_api/const.py
podme_api/exceptions.py
podme_api/helpers.py
podme_api/models.py
podme_api/py.typed
podme_api-1.4.2.dist-info/LICENSE
podme_api-1.4.2.dist-info/METADATA
podme_api-1.4.2.dist-info/WHEEL
podme_api-1.4.2.dist-info/entry_points.txt
podme_api-1.4.2.dist-info/RECORD
