Metadata-Version: 2.3
Name: podme-api
Version: 1.4.2
Summary: A client library for using the podme.com web API
License: MIT
Keywords: podcast,podme,api-client,unofficial
Author: Bendik R. Brenne
Author-email: bendik@konstant.no
Requires-Python: >=3.11,<4.0
Classifier: Environment :: Console
Classifier: Intended Audience :: Developers
Classifier: License :: OSI Approved :: MIT License
Classifier: Programming Language :: Python
Classifier: Programming Language :: Python :: 3
Classifier: Programming Language :: Python :: 3.11
Classifier: Programming Language :: Python :: 3.12
Classifier: Programming Language :: Python :: 3.13
Provides-Extra: doc
Provides-Extra: test
Requires-Dist: aiofiles (>=24.1.0,<25.0.0)
Requires-Dist: aiohttp (>=3.11.18,<4.0.0)
Requires-Dist: isodate (>=0.7.2,<0.8.0)
Requires-Dist: mashumaro (>=3.5,<4.0)
Requires-Dist: orjson (>=3.10.16,<4.0.0)
Requires-Dist: pathlib (>=1.0.1,<2.0.0)
Requires-Dist: pkce (==1.0.3)
Requires-Dist: platformdirs (>=4.3.7,<5.0.0)
Requires-Dist: python-ffmpeg (>=2.0.12,<3.0.0)
Requires-Dist: rich (>=13.9.2,<14.0.0)
Project-URL: Documentation, https://podme-api.readthedocs.io/en/latest/
Project-URL: Repository, https://github.com/bendikrb/podme_api
